musicxml_to_motif/__init__.py
musicxml_to_motif/__main__.py
musicxml_to_motif/cli.py
musicxml_to_motif-0.1.1.dist-info/licenses/LICENSE
musicxml_to_motif-0.1.1.dist-info/METADATA
musicxml_to_motif-0.1.1.dist-info/WHEEL
musicxml_to_motif-0.1.1.dist-info/entry_points.txt
musicxml_to_motif-0.1.1.dist-info/top_level.txt
musicxml_to_motif-0.1.1.dist-info/RECORD
