Metadata-Version: 2.4
Name: musicxml-to-motif
Version: 0.1.1
Summary: Convert MusicXML files into motif-friendly representations.
Author: Rob Mosher
License: MIT
Project-URL: Repository, https://github.com/rob-mosher/musicxml-to-motif
Project-URL: Issues, https://github.com/rob-mosher/musicxml-to-motif/issues
Keywords: musicxml,music,motif,analysis
Classifier: Development Status :: 2 - Pre-Alpha
Classifier: License :: OSI Approved :: MIT License
Classifier: Programming Language :: Python :: 3
Classifier: Programming Language :: Python :: 3.12
Classifier: Topic :: Multimedia :: Sound/Audio
Requires-Python: >=3.12
License-File: LICENSE
Dynamic: license-file
